README.md
setup.py
run_cifl_auth/__init__.py
run_cifl_auth.egg-info/PKG-INFO
run_cifl_auth.egg-info/SOURCES.txt
run_cifl_auth.egg-info/dependency_links.txt
run_cifl_auth.egg-info/entry_points.txt
run_cifl_auth.egg-info/not-zip-safe
run_cifl_auth.egg-info/requires.txt
run_cifl_auth.egg-info/top_level.txt