Metadata-Version: 1.0
Name: run-cifl-auth
Version: 0.1.0
Summary: Authentication module for Google APIs
Home-page: https://github.com/coding-is-for-losers/singer-taps-and-targets-v1.1/tree/master/run_cifl_auth
Author: CIFL
Author-email: UNKNOWN
License: MIT
Platform: UNKNOWN
